dash_annotate_cv/__init__.py
dash_annotate_cv/annotate_image_bboxs.py
dash_annotate_cv/annotate_image_controller.py
dash_annotate_cv/annotate_image_controls.py
dash_annotate_cv/annotate_image_labels.py
dash_annotate_cv/annotation_storage.py
dash_annotate_cv/command_line.py
dash_annotate_cv/helpers.py
dash_annotate_cv/image_source.py
dash_annotate_cv/label_source.py
dash_annotate_cv/formats/__init__.py
dash_annotate_cv/formats/coco.py
dash_annotate_cv/formats/default.py
dash_annotate_cv/formats/image_annotations.py
dash_annotate_cv-0.1.9.dist-info/LICENSE
dash_annotate_cv-0.1.9.dist-info/METADATA
dash_annotate_cv-0.1.9.dist-info/WHEEL
dash_annotate_cv-0.1.9.dist-info/entry_points.txt
dash_annotate_cv-0.1.9.dist-info/top_level.txt
dash_annotate_cv-0.1.9.dist-info/RECORD
