Metadata-Version: 2.1
Name: dash-annotate-cv
Version: 0.1.9
Summary: A Python library for computer vision annotation tasks using Dash
Home-page: https://github.com/smrfeld/dash-annotate-cv
Author: Oliver K. Ernst
Classifier: Programming Language :: Python :: 3
Classifier: License :: OSI Approved :: MIT License
Classifier: Operating System :: OS Independent
Requires-Python: >=3.6
License-File: LICENSE
Requires-Dist: dash
Requires-Dist: scikit-image
Requires-Dist: plotly
Requires-Dist: dash-bootstrap-components
Requires-Dist: dataclasses
Requires-Dist: mashumaro
Requires-Dist: pandas
Requires-Dist: Pillow
Requires-Dist: pyyaml
